{
  "funds": {
    "af": {
      "lastChecked": "2026-07-20",
      "lastChanged": null,
      "changedSinceLastView": false,
      "note": "No change detected on this check.",
      "sourceUrl": "https://www.adaptation-fund.org/apply-funding/"
    },
    "gcf": {
      "lastChecked": "2026-07-20",
      "lastChanged": "2026-07-20",
      "changedSinceLastView": false,
      "checkFailed": false,
      "note": "No change detected on this check.",
      "latestContent": "Active RFP: current REDD+ funding window Enhancing Direct Access (EDA)",
      "sourceUrl": "https://www.greenclimate.fund/access-funding/other-funding-options"
    },
    "cif": {
      "lastChecked": "2026-07-20",
      "lastChanged": "2026-07-17",
      "changedSinceLastView": false,
      "checkFailed": false,
      "note": "No change detected on this check.",
      "latestContent": "How Brazil and Mexico Plan to Decarbonize High-Emitting Industries -- Jul 16, 2026",
      "sourceUrl": "https://www.cif.org/news"
    },
    "gef": {
      "lastChecked": "2026-07-20",
      "lastChanged": "2026-07-18",
      "changedSinceLastView": false,
      "checkFailed": false,
      "note": "No change detected on this check.",
      "latestContent": "Finding deep roots of agreement for soil health -- July 14, 2026",
      "sourceUrl": "https://www.thegef.org/newsroom"
    },
    "frld": {
      "lastChecked": "2026-07-20",
      "lastChanged": "2026-07-19",
      "changedSinceLastView": false,
      "checkFailed": false,
      "note": "First scrape - baseline established. Will detect changes from tomorrow.",
      "latestContent": "July 11, 2026: Ninth Meeting of the Board of the FRLD The Ninth meeting of the Board of the FRLD will convene on 08-10 July, 2026 at Asian Development Bank Headquarters in Manila, Philippines. As the secret",
      "sourceUrl": "https://www.frld.org/"
    },
    "frld_news": {
      "lastChecked": "2026-07-20",
      "lastChanged": "2026-07-19",
      "changedSinceLastView": false,
      "checkFailed": false,
      "note": "First scrape - baseline established. Will detect changes from tomorrow.",
      "latestContent": "July 10, 2026: The Fund for responding to Loss and Damage Board Concludes Ninth Meeting, Advances Resource Mobilization and Prepares for Funding Decisions Manila, Philippines, 10 July 2026 \u2013 The",
      "sourceUrl": "https://www.frld.org/news"
    },
    "frld_b9": {
      "lastChecked": "2026-07-20",
      "lastChanged": "2026-07-09",
      "changedSinceLastView": false,
      "checkFailed": false,
      "note": "No change detected on this check.",
      "latestContent": null,
      "sourceUrl": "https://www.frld.org/nodeninth-meeting-board-frld"
    }
  }
}